streamlit_chat/__init__.py
streamlit_chat/frontend/build/asset-manifest.json
streamlit_chat/frontend/build/bootstrap.min.css
streamlit_chat/frontend/build/bootstrap.min.css.map
streamlit_chat/frontend/build/index.html
streamlit_chat/frontend/build/precache-manifest.4deaf86e5f803571108bd8b87b0eca85.js
streamlit_chat/frontend/build/precache-manifest.913e70ff508b34716fa805cc28b9d423.js
streamlit_chat/frontend/build/service-worker.js
streamlit_chat/frontend/build/static/css/2.4fdd6c40.chunk.css
streamlit_chat/frontend/build/static/css/2.4fdd6c40.chunk.css.map
streamlit_chat/frontend/build/static/js/2.96b2a504.chunk.js
streamlit_chat/frontend/build/static/js/2.96b2a504.chunk.js.LICENSE.txt
streamlit_chat/frontend/build/static/js/2.96b2a504.chunk.js.map
streamlit_chat/frontend/build/static/js/main.e5b32794.chunk.js
streamlit_chat/frontend/build/static/js/main.e5b32794.chunk.js.map
streamlit_chat/frontend/build/static/js/main.e9a08b4d.chunk.js
streamlit_chat/frontend/build/static/js/main.e9a08b4d.chunk.js.map
streamlit_chat/frontend/build/static/js/runtime-main.11ec9aca.js
streamlit_chat/frontend/build/static/js/runtime-main.11ec9aca.js.map
streamlit_chat/frontend/build/static/media/KaTeX_AMS-Regular.10824af7.woff
streamlit_chat/frontend/build/static/media/KaTeX_AMS-Regular.56573229.ttf
streamlit_chat/frontend/build/static/media/KaTeX_AMS-Regular.66c67820.woff2
streamlit_chat/frontend/build/static/media/KaTeX_Caligraphic-Bold.497bf407.ttf
streamlit_chat/frontend/build/static/media/KaTeX_Caligraphic-Bold.a9e9b095.woff2
streamlit_chat/frontend/build/static/media/KaTeX_Caligraphic-Bold.de2ba279.woff
streamlit_chat/frontend/build/static/media/KaTeX_Caligraphic-Regular.08d95d99.woff2
streamlit_chat/frontend/build/static/media/KaTeX_Caligraphic-Regular.a25140fb.woff
streamlit_chat/frontend/build/static/media/KaTeX_Caligraphic-Regular.e6fb499f.ttf
streamlit_chat/frontend/build/static/media/KaTeX_Fraktur-Bold.40934fc0.woff
streamlit_chat_askgdpr-0.3.dist-info/LICENSE
streamlit_chat_askgdpr-0.3.dist-info/METADATA
streamlit_chat_askgdpr-0.3.dist-info/WHEEL
streamlit_chat_askgdpr-0.3.dist-info/top_level.txt
streamlit_chat_askgdpr-0.3.dist-info/RECORD
