Metadata-Version: 2.1
Name: streamlit-chat-askgdpr
Version: 0.3
Summary: A streamlit component, to make chatbots
Home-page: https://github.com/AI-Yash/st-chat
Author: Grzegorz Kossakowski, Maciej Zdanowicz
Author-email: yashpawarp@gmail.com
Keywords: chat streamlit streamlit-component
Classifier: Programming Language :: Python :: 3
Classifier: Operating System :: OS Independent
Requires-Python: >=3.8
License-File: LICENSE
Requires-Dist: streamlit (>=0.63)
